example_publish_pypi_medium/__init__.py
example_publish_pypi_medium/example/__init__.py
example_publish_pypi_medium/example/custom_sklearn.py
miyanepp-0.6.dist-info/METADATA
miyanepp-0.6.dist-info/WHEEL
miyanepp-0.6.dist-info/top_level.txt
miyanepp-0.6.dist-info/RECORD
